tagore/__init__.py
tagore/base.svg.p
tagore/main.py
tagore/scripts/rfmix2tagore.py
tagore-1.1.2.dist-info/LICENSE
tagore-1.1.2.dist-info/METADATA
tagore-1.1.2.dist-info/WHEEL
tagore-1.1.2.dist-info/entry_points.txt
tagore-1.1.2.dist-info/top_level.txt
tagore-1.1.2.dist-info/RECORD
