Metadata-Version: 2.1
Name: tagore
Version: 1.1.2
Summary: A simple way to visualize features on human chromosome ideograms
Home-page: https://github.com/jordanlab/tagore
Author: Applied Bioinformatics Laboratory
Author-email: abil@ihrc.com
Keywords: Human,chromosome,ideogram,visualization
Classifier: Programming Language :: Python :: 3
Classifier: License :: OSI Approved :: GNU General Public License v3 (GPLv3)
Classifier: Operating System :: MacOS
Classifier: Operating System :: POSIX
Classifier: Environment :: Console
Classifier: Development Status :: 5 - Production/Stable
Classifier: Topic :: Scientific/Engineering :: Visualization
Requires-Python: >=3.6
License-File: LICENSE
Requires-Dist: click
